iprecommit/__init__.py
iprecommit/checks.py
iprecommit/common.py
iprecommit/extras/__init__.py
iprecommit/extras/commit_msg_format.py
iprecommit/extras/newline_at_eof.py
iprecommit/extras/no_forbidden_strings.py
iprecommit/extras/pathhelper.py
iprecommit/extras/typos.py
iprecommit/githelper.py
iprecommit/main.py
iprecommit/tomlconfig.py
iprecommit/tomlparse/LICENSE
iprecommit/tomlparse/README.md
iprecommit/tomlparse/__init__.py
iprecommit/tomlparse/decoder.py
iprecommit/tomlparse/tz.py
iprecommit-0.7.5.dist-info/LICENSE
iprecommit-0.7.5.dist-info/METADATA
iprecommit-0.7.5.dist-info/WHEEL
iprecommit-0.7.5.dist-info/entry_points.txt
iprecommit-0.7.5.dist-info/RECORD
