Metadata-Version: 2.1
Name: iprecommit
Version: 0.7.5
Summary: Dead-simple Git pre-commit hooks
License: MIT
Author: Ian Fisher
Author-email: ian@iafisher.com
Requires-Python: >=3.9,<4.0
Classifier: License :: OSI Approved :: MIT License
Classifier: Programming Language :: Python :: 3
Classifier: Programming Language :: Python :: 3.9
Classifier: Programming Language :: Python :: 3.10
Classifier: Programming Language :: Python :: 3.11
Classifier: Programming Language :: Python :: 3.12
